{
  "title": "Professional Business Presentation",
  "author": "Jane Smith",
  "subject": "Quarterly Business Review",
  "company": "Acme Corporation",
  "slides": [
    {
      "layout": "title",
      "title": "Q4 2024 Business Review",
      "subtitle": "Performance, Insights, and Strategic Direction",
      "author": "Jane Smith, CEO",
      "date": "January 2025",
      "notes": "Welcome everyone to our quarterly business review. Today we'll cover our Q4 performance, key insights, and strategic direction for 2025."
    },
    {
      "layout": "text",
      "title": "Agenda",
      "bullets": [
        "Executive Summary",
        "Financial Performance",
        "  • Revenue Growth",
        "  • Profit Margins",
        "  • Cost Analysis",
        "Market Analysis",
        "  • Competitive Landscape",
        "  • Customer Insights",
        "Strategic Initiatives",
        "Q&A Session"
      ],
      "level": [0, 0, 1, 1, 1, 0, 1, 1, 0, 0],
      "notes": "Here's what we'll cover in today's presentation. We'll start with an executive summary, dive into financial performance, analyze our market position, and discuss strategic initiatives."
    },
    {
      "layout": "text",
      "title": "Executive Summary",
      "bullets": [
        "<strong>Record Revenue:</strong> $12.5M in Q4, up 35% YoY",
        "<strong>Market Expansion:</strong> Successfully entered 3 new markets",
        "<strong>Customer Growth:</strong> 2,500 new enterprise clients",
        "<strong>Product Launch:</strong> Successfully launched Product X with 95% satisfaction",
        "<strong>Team Growth:</strong> Expanded team by 40% while maintaining culture"
      ],
      "notes": "Q4 was our strongest quarter yet with record-breaking revenue and successful expansion into new markets."
    },
    {
      "layout": "chart",
      "title": "Revenue Growth Trajectory",
      "chartType": "line",
      "data": {
        "labels": ["Q1 2024", "Q2 2024", "Q3 2024", "Q4 2024"],
        "datasets": [
          {
            "label": "Revenue ($M)",
            "data": [7.2, 8.5, 10.1, 12.5],
            "backgroundColor": "#4472C4",
            "borderColor": "#4472C4"
          },
          {
            "label": "Target ($M)",
            "data": [7.0, 8.0, 9.5, 11.0],
            "backgroundColor": "#ED7D31",
            "borderColor": "#ED7D31"
          }
        ]
      },
      "options": {
        "showLegend": true,
        "showDataLabels": true,
        "legendPosition": "bottom"
      },
      "notes": "Revenue exceeded targets in all quarters, with Q4 showing exceptional performance at 13.6% above target."
    },
    {
      "layout": "chart",
      "title": "Market Share Analysis",
      "chartType": "pie",
      "data": {
        "labels": ["Acme Corp", "Competitor A", "Competitor B", "Competitor C", "Others"],
        "datasets": [
          {
            "label": "Market Share %",
            "data": [32, 25, 18, 15, 10],
            "backgroundColor": ["#4472C4", "#ED7D31", "#A5A5A5", "#FFC000", "#5B9BD5"]
          }
        ]
      },
      "options": {
        "showLegend": true,
        "showDataLabels": true
      },
      "notes": "We've maintained market leadership position with 32% market share, gaining 5 percentage points from last quarter."
    },
    {
      "layout": "table",
      "title": "Regional Performance Breakdown",
      "headers": ["Region", "Revenue ($M)", "Growth %", "New Clients", "Retention %"],
      "tableData": [
        ["North America", "5.2", "28%", "850", "94%"],
        ["Europe", "3.8", "42%", "620", "92%"],
        ["Asia Pacific", "2.1", "55%", "580", "89%"],
        ["Latin America", "1.4", "68%", "450", "87%"],
        ["Total", "12.5", "35%", "2500", "91%"]
      ],
      "styling": {
        "headerBackground": "#4472C4",
        "headerTextColor": "#FFFFFF",
        "alternateRows": true,
        "fontSize": 14
      },
      "notes": "Asia Pacific and Latin America showing strongest growth rates, while North America maintains highest absolute revenue."
    },
    {
      "layout": "chart",
      "title": "Customer Satisfaction Metrics",
      "chartType": "bar",
      "data": {
        "labels": ["Product Quality", "Customer Service", "Value for Money", "Innovation", "Overall"],
        "datasets": [
          {
            "label": "Q3 2024",
            "data": [82, 78, 75, 80, 79],
            "backgroundColor": "#A5A5A5"
          },
          {
            "label": "Q4 2024",
            "data": [88, 85, 82, 87, 86],
            "backgroundColor": "#4472C4"
          }
        ]
      },
      "options": {
        "showLegend": true,
        "legendPosition": "top"
      },
      "notes": "Significant improvement across all satisfaction metrics, with overall satisfaction increasing by 7 percentage points."
    },
    {
      "layout": "image",
      "title": "Product X Launch Success",
      "imageUrl": "https://via.placeholder.com/1200x600/4472C4/FFFFFF?text=Product+X+Dashboard",
      "caption": "Product X Dashboard showing real-time analytics and insights",
      "sizing": "contain",
      "notes": "Product X has exceeded adoption targets with 1,200 enterprise customers in the first quarter."
    },
    {
      "layout": "text",
      "title": "Key Strategic Initiatives for 2025",
      "bullets": [
        "<strong>Geographic Expansion:</strong> Enter 5 new international markets",
        "<strong>Product Innovation:</strong> Launch 3 major product updates",
        "<strong>AI Integration:</strong> Implement AI-powered features across platform",
        "<strong>Partnership Program:</strong> Establish strategic partnerships with 10+ vendors",
        "<strong>Sustainability:</strong> Achieve carbon neutrality by Q3 2025"
      ],
      "notes": "These initiatives are designed to maintain our growth trajectory and strengthen our market position."
    },
    {
      "layout": "table",
      "title": "2025 Financial Projections",
      "headers": ["Quarter", "Revenue Target ($M)", "Growth %", "EBITDA Margin"],
      "tableData": [
        ["Q1 2025", "14.5", "16%", "22%"],
        ["Q2 2025", "16.8", "16%", "24%"],
        ["Q3 2025", "19.2", "14%", "25%"],
        ["Q4 2025", "22.0", "15%", "26%"],
        ["FY 2025", "72.5", "15%", "24.5%"]
      ],
      "styling": {
        "headerBackground": "#ED7D31",
        "headerTextColor": "#FFFFFF",
        "alternateRows": true
      },
      "notes": "Conservative projections showing steady growth with improving margins throughout 2025."
    },
    {
      "layout": "custom",
      "title": "Innovation Roadmap",
      "elements": [
        {
          "type": "text",
          "x": 0.5,
          "y": 2,
          "width": 2.5,
          "height": 1,
          "content": "Q1 2025\n• AI Assistant Beta\n• Mobile App v2.0",
          "styling": {
            "fontSize": 14,
            "color": "#FFFFFF",
            "fill": "#4472C4",
            "align": "left"
          }
        },
        {
          "type": "text",
          "x": 3.5,
          "y": 2,
          "width": 2.5,
          "height": 1,
          "content": "Q2 2025\n• Enterprise API\n• Advanced Analytics",
          "styling": {
            "fontSize": 14,
            "color": "#FFFFFF",
            "fill": "#ED7D31",
            "align": "left"
          }
        },
        {
          "type": "text",
          "x": 6.5,
          "y": 2,
          "width": 2.5,
          "height": 1,
          "content": "Q3 2025\n• Global Platform\n• Partner Portal",
          "styling": {
            "fontSize": 14,
            "color": "#FFFFFF",
            "fill": "#70AD47",
            "align": "left"
          }
        },
        {
          "type": "shape",
          "x": 0.5,
          "y": 3.5,
          "width": 8.5,
          "height": 0.05,
          "content": {
            "type": "rect",
            "fill": "#C0C0C0"
          }
        },
        {
          "type": "text",
          "x": 0.5,
          "y": 4,
          "width": 8.5,
          "height": 2,
          "content": "Our innovation roadmap focuses on AI integration, platform expansion, and ecosystem development to maintain competitive advantage.",
          "styling": {
            "fontSize": 16,
            "color": "#333333",
            "align": "center"
          }
        }
      ],
      "notes": "The innovation roadmap is aligned with our strategic goals and customer feedback."
    },
    {
      "layout": "text",
      "title": "Next Steps",
      "bullets": [
        "Finalize Q1 2025 operational plans by January 31",
        "Launch customer feedback program in February",
        "Complete market expansion analysis by March 15",
        "Host investor day on April 10",
        "Review and adjust strategy at mid-year checkpoint"
      ],
      "notes": "Clear action items with specific deadlines to ensure execution of our strategic plan."
    },
    {
      "layout": "title",
      "title": "Thank You",
      "subtitle": "Questions & Discussion",
      "backgroundColor": "#4472C4",
      "notes": "Thank you for your attention. I'm now happy to answer any questions about our performance or strategic direction."
    }
  ],
  "theme": {
    "primaryColor": "#4472C4",
    "secondaryColor": "#ED7D31",
    "accentColor": "#70AD47",
    "fontFamily": "Arial",
    "fontSize": 16,
    "backgroundColor": "#FFFFFF"
  },
  "metadata": {
    "created": "2025-01-15",
    "revision": "1.0",
    "keywords": ["business", "quarterly review", "financial", "strategy"],
    "category": "Business Presentation"
  }
}